pyFussion/__init__.py
pyFussion/__main__.py
pyFussion/configs.py
pyFussion/version.py
pyFussion/dB/__init__.py
pyFussion/dB/_core.py
pyFussion/dB/afk_db.py
pyFussion/dB/antiflood_db.py
pyFussion/dB/asst_fns.py
pyFussion/dB/asstcmd_db.py
pyFussion/dB/blacklist_chat_db.py
pyFussion/dB/blacklist_db.py
pyFussion/dB/botchat_db.py
pyFussion/dB/broadcast_db.py
pyFussion/dB/ch_db.py
pyFussion/dB/chatBot_db.py
pyFussion/dB/clean_db.py
pyFussion/dB/echo_db.py
pyFussion/dB/filter_db.py
pyFussion/dB/forcesub_db.py
pyFussion/dB/gban_mute_db.py
pyFussion/dB/gcast_blacklist_db.py
pyFussion/dB/greetings_db.py
pyFussion/dB/logusers_db.py
pyFussion/dB/mute_db.py
pyFussion/dB/night_db.py
pyFussion/dB/notes_db.py
pyFussion/dB/nsfw_db.py
pyFussion/dB/pmpermit_db.py
pyFussion/dB/snips_db.py
pyFussion/dB/sudos.py
pyFussion/dB/username_db.py
pyFussion/dB/vc_group.py
pyFussion/dB/vc_sudos.py
pyFussion/dB/warn_db.py
pyFussion/functions/FastTelethon.py
pyFussion/functions/__init__.py
pyFussion/functions/admins.py
pyFussion/functions/gdrive.py
pyFussion/functions/google_image.py
pyFussion/functions/helper.py
pyFussion/functions/info.py
pyFussion/functions/misc.py
pyFussion/functions/tools.py
pyFussion/functions/ytdl.py
pyFussion/misc/__init__.py
pyFussion/misc/_assistant.py
pyFussion/misc/_decorators.py
pyFussion/misc/_supporter.py
pyFussion/misc/_wrappers.py
pyFussion/startup/BaseClient.py
pyFussion/startup/__init__.py
pyFussion/startup/connections.py
pyFussion/startup/exceptions.py
pyFussion/startup/funcs.py
pyFussion/startup/loader.py
pyFussion/startup/utils.py
py_Fussion-3.5.dist-info/LICENSE
py_Fussion-3.5.dist-info/METADATA
py_Fussion-3.5.dist-info/WHEEL
py_Fussion-3.5.dist-info/top_level.txt
py_Fussion-3.5.dist-info/RECORD
