Metadata-Version: 2.1
Name: py-Fussion
Version: 3.5
Summary: A Secure and Powerful Python-Telethon Based Library For Dark Fussion Userbot.
Home-page: https://github.com/TeamFussion/pyFussion
Author: TeamFussion
Author-email: redwarp06@gmail.com
License: GNU AFFERO GENERAL PUBLIC LICENSE (v3)
Project-URL: Bug Tracker, https://github.com/TeamFussion/pyFussion/issues
Project-URL: Source Code, https://github.com/TeamFussion/pyFussion
Platform: UNKNOWN
Classifier: Programming Language :: Python :: 3
Classifier: Programming Language :: Python :: 3.6
Classifier: Programming Language :: Python :: 3.7
Classifier: Programming Language :: Python :: 3.8
Classifier: Programming Language :: Python :: 3.9
Classifier: License :: OSI Approved :: GNU General Public License v3 (GPLv3)
Classifier: Operating System :: OS Independent
Requires-Python: >=3.6
Requires-Dist: redis
Requires-Dist: python-decouple (==3.3)
Requires-Dist: python-dotenv (==0.15.0)
Requires-Dist: aiofiles
Requires-Dist: aiohttp
